DPGComponents/DPGComponents.py
DPGComponents/__init__.py
DPGComponents/icons/abc_16dp_FFFFFF_FILL0_wght200_GRAD0_opsz20.png
DPGComponents/icons/calendar_month_14dp_FFFFFF_FILL0_wght200_GRAD0_opsz20.png
DPGComponents/icons/check_16dp_FFFFFF_FILL0_wght200_GRAD0_opsz20.png
DPGComponents/icons/number_16dp_FFFFFF_FILL0_wght200_GRAD0_opsz24.png
dpgcomponents-0.0.6.dist-info/METADATA
dpgcomponents-0.0.6.dist-info/WHEEL
dpgcomponents-0.0.6.dist-info/top_level.txt
dpgcomponents-0.0.6.dist-info/RECORD
