Metadata-Version: 2.4
Name: DPGComponents
Version: 0.0.6
Summary: Components for DPG
Author-email: Smith <winston.doublethink@gmail.com>
License-Expression: MIT
Project-URL: Homepage, https://github.com/benjaminthedonkey/dpg-components
Project-URL: Issues, https://github.com/benjaminthedonkey/dpg-components/issues
Classifier: Programming Language :: Python :: 3
Classifier: Operating System :: OS Independent
Requires-Python: >=3.8
Requires-Dist: dearpygui>=2.1.0
Requires-Dist: pandas>=2.2.3
